panjabiAI/__init__.py
panjabiAI/utils.py
panjabiAI/NER/__init__.py
panjabiAI/NER/allennlp/__init__.py
panjabiAI/NER/allennlp/punjabi_ner.py
panjabiAI/NER/ktrain/__init__.py
panjabiAI/NER/ktrain/punjabi_ner.py
panjabiAI/POS/__init__.py
panjabiAI/POS/pos.py
panjabiAI/machine_translation/__init__.py
panjabiAI/machine_translation/translate.py
panjabiAI/machine_transliteration/__init__.py
panjabiAI/machine_transliteration/transliteration.py
panjabiAI/punjabi_subword_tokenizer/__init__.py
panjabiAI/punjabi_subword_tokenizer/sentencepiece_tokenizer.py
panjabiAI/text_classification/__init__.py
panjabiAI/text_classification/news_classification.py
panjabiAI/word_vector/__init__.py
panjabiAI/word_vector/punjabi_word2vec.py
panjabi.AI-1.0.0.dist-info/LICENSE
panjabi.AI-1.0.0.dist-info/METADATA
panjabi.AI-1.0.0.dist-info/WHEEL
panjabi.AI-1.0.0.dist-info/top_level.txt
panjabi.AI-1.0.0.dist-info/RECORD
