Metadata-Version: 2.1
Name: panjabi.AI
Version: 1.0.0
Summary: A python based punjabi NLP Toolkit.
Home-page: https://gitlab.com/sabudh/lingua-franca/lingua-franca/
Author: Sabudh Foundation
Author-email: info@sabudh.org
License: MIT
Classifier: Programming Language :: Python :: 3
Classifier: License :: OSI Approved :: MIT License
Classifier: Operating System :: Microsoft :: Windows
Classifier: Operating System :: POSIX :: Linux
Requires-Python: >=3.7
License-File: LICENSE
